polis_client/__init__.py
polis_client/client.py
polis_client/errors.py
polis_client/generated/__init__.py
polis_client/generated/client.py
polis_client/generated/errors.py
polis_client/generated/types.py
polis_client/generated/api/__init__.py
polis_client/generated/api/comments/__init__.py
polis_client/generated/api/comments/create_comment.py
polis_client/generated/api/comments/get_comments.py
polis_client/generated/api/conversations/__init__.py
polis_client/generated/api/conversations/get_conversation.py
polis_client/generated/api/conversations/get_conversation_uuid.py
polis_client/generated/api/conversations/get_conversation_xids_by_uuid.py
polis_client/generated/api/exports/__init__.py
polis_client/generated/api/exports/get_export_file.py
polis_client/generated/api/initialization/__init__.py
polis_client/generated/api/initialization/get_initialization.py
polis_client/generated/api/math/__init__.py
polis_client/generated/api/math/get_math.py
polis_client/generated/api/reports/__init__.py
polis_client/generated/api/reports/get_report.py
polis_client/generated/api/users/__init__.py
polis_client/generated/api/users/get_participant.py
polis_client/generated/api/votes/__init__.py
polis_client/generated/api/votes/create_vote.py
polis_client/generated/api/votes/get_votes.py
polis_client/generated/models/__init__.py
polis_client/generated/models/auth_token_response.py
polis_client/generated/models/comment.py
polis_client/generated/models/comment_mod.py
polis_client/generated/models/conversation.py
polis_client/generated/models/conversation_uuid.py
polis_client/generated/models/create_comment_body.py
polis_client/generated/models/create_comment_body_vote.py
polis_client/generated/models/create_vote_body.py
polis_client/generated/models/get_comments_mod.py
polis_client/generated/models/get_comments_mod_gt.py
polis_client/generated/models/get_export_file_filename.py
polis_client/generated/models/math_v3.py
polis_client/generated/models/math_v3_base_clusters.py
polis_client-0.1.2.dist-info/METADATA
polis_client-0.1.2.dist-info/WHEEL
polis_client-0.1.2.dist-info/licenses/LICENSE
polis_client-0.1.2.dist-info/RECORD
