Metadata-Version: 2.4
Name: polis-client
Version: 0.1.2
Summary: Client library for interacting with API of any Pol.is server
Project-URL: Homepage, https://github.com/patcon/polis-client
Project-URL: Documentation, https://github.com/patcon/polis-client/blob/main/python/examples.ipynb
Project-URL: Repository, https://github.com/patcon/polis-client
Project-URL: Issues, https://github.com/patcon/polis-client/issues
Author-email: Patrick Connolly <patrick.c.connolly@gmail.com>
License: MIT
License-File: LICENSE
Keywords: api,client,democracy,polis
Classifier: Development Status :: 3 - Alpha
Classifier: Intended Audience :: Developers
Classifier: License :: OSI Approved :: MIT License
Classifier: Programming Language :: Python :: 3
Classifier: Programming Language :: Python :: 3.10
Classifier: Programming Language :: Python :: 3.11
Classifier: Programming Language :: Python :: 3.12
Classifier: Programming Language :: Python :: 3.13
Classifier: Topic :: Software Development :: Libraries :: Python Modules
Requires-Python: >=3.10
Requires-Dist: attrs>=25.4.0
Requires-Dist: httpx>=0.28.1
